rabbitmq_arq/README.md
rabbitmq_arq/__init__.py
rabbitmq_arq/cli.py
rabbitmq_arq/client.py
rabbitmq_arq/connections.py
rabbitmq_arq/constants.py
rabbitmq_arq/exceptions.py
rabbitmq_arq/job.py
rabbitmq_arq/models.py
rabbitmq_arq/protocols.py
rabbitmq_arq/worker.py
rabbitmq_arq/result_storage/__init__.py
rabbitmq_arq/result_storage/base.py
rabbitmq_arq/result_storage/factory.py
rabbitmq_arq/result_storage/models.py
rabbitmq_arq/result_storage/redis.py
rabbitmq_arq/result_storage/url_parser.py
rabbitmq_arq-0.2.2.dist-info/licenses/LICENSE
rabbitmq_arq-0.2.2.dist-info/METADATA
rabbitmq_arq-0.2.2.dist-info/WHEEL
rabbitmq_arq-0.2.2.dist-info/entry_points.txt
rabbitmq_arq-0.2.2.dist-info/top_level.txt
rabbitmq_arq-0.2.2.dist-info/RECORD
