Metadata-Version: 2.4
Name: rabbitmq_arq
Version: 0.2.2
Summary: 一个基于RabbitMQ的任务队列库，提供类似arq的简洁API
Author-email: RabbitMQ-ARQ Team <robin528919@gmail.com>
License-Expression: MIT
Project-URL: Homepage, https://github.com/Robin528919/rabbitmq-mq
Project-URL: Repository, https://github.com/Robin528919/rabbitmq-mq
Project-URL: Documentation, https://github.com/Robin528919/rabbitmq-mq#readme
Project-URL: Bug Tracker, https://github.com/Robin528919/rabbitmq-mq/issues
Classifier: Development Status :: 4 - Beta
Classifier: Intended Audience :: Developers
Classifier: Programming Language :: Python :: 3
Classifier: Programming Language :: Python :: 3.8
Classifier: Programming Language :: Python :: 3.9
Classifier: Programming Language :: Python :: 3.10
Classifier: Programming Language :: Python :: 3.11
Classifier: Programming Language :: Python :: 3.12
Classifier: Topic :: Software Development :: Libraries :: Python Modules
Classifier: Topic :: System :: Distributed Computing
Classifier: Framework :: AsyncIO
Classifier: Operating System :: OS Independent
Requires-Python: >=3.8
License-File: LICENSE
Requires-Dist: aio-pika>=9.0.0
Requires-Dist: pydantic>=2.0.0
Requires-Dist: click>=8.0.0
Requires-Dist: redis>=4.5.0
Provides-Extra: dev
Requires-Dist: pytest>=7.0.0; extra == "dev"
Requires-Dist: pytest-asyncio>=0.21.0; extra == "dev"
Requires-Dist: pytest-cov>=4.0.0; extra == "dev"
Requires-Dist: black>=23.0.0; extra == "dev"
Requires-Dist: isort>=5.12.0; extra == "dev"
Requires-Dist: flake8>=6.0.0; extra == "dev"
Requires-Dist: mypy>=1.5.0; extra == "dev"
Requires-Dist: pre-commit>=3.0.0; extra == "dev"
Provides-Extra: mongodb
Requires-Dist: pymongo>=4.3.0; extra == "mongodb"
Requires-Dist: motor>=3.2.0; extra == "mongodb"
Provides-Extra: database
Requires-Dist: asyncpg>=0.28.0; extra == "database"
Requires-Dist: aiomysql>=0.2.0; extra == "database"
Requires-Dist: aiosqlite>=0.19.0; extra == "database"
Provides-Extra: s3
Requires-Dist: aioboto3>=11.0.0; extra == "s3"
Provides-Extra: all
Requires-Dist: pymongo>=4.3.0; extra == "all"
Requires-Dist: motor>=3.2.0; extra == "all"
Requires-Dist: asyncpg>=0.28.0; extra == "all"
Requires-Dist: aiomysql>=0.2.0; extra == "all"
Requires-Dist: aiosqlite>=0.19.0; extra == "all"
Requires-Dist: aioboto3>=11.0.0; extra == "all"
Dynamic: license-file
